[
  {
    "id": "wy-1",
    "business_name": "Gillette Billiards",
    "slug": "gillette-billiards",
    "street_address": "Unknown",
    "city": "Gillette",
    "state": "Wyoming",
    "zip": "82716",
    "latitude": 44.2911,
    "longitude": -105.5022,
    "phone": "Unknown",
    "website": "Unknown",
    "owner_operator": "Unknown",
    "hours": {
      "Mon-Sun": "12:00 PM – 12:00 AM"
    },
    "table_count": 8,
    "table_types": {
      "9-foot": 0,
      "7-foot": 8,
      "8-foot": 0,
      "snooker": 0,
      "carom": 0,
      "bar_tables": 0
    },
    "cloth_type": "Standard",
    "league_types": [
      "VNEA"
    ],
    "tournament_frequency": "Occasional",
    "weekly_tournament_schedule": "",
    "verified_status": "partial_verified",
    "verification_score": 85,
    "last_verified": "2026-04-28",
    "verification_sources": [
      "manual_review"
    ],
    "review_required": false,
    "photo_gallery": [
      "/images/hero-table.jpg"
    ],
    "primary_hero_image": "/images/hero-table.jpg",
    "parking_info": "Lot parking",
    "alcohol_food_availability": "Bar",
    "handicap_accessible": true,
    "room_description": "Local WY pool hall with bar boxes.",
    "membership_info": "Open to public",
    "local_reputation_notes": "Local action.",
    "source_attribution": [
      "Manual Intel"
    ]
  },
  {
    "id": "ag-wyoming-1777479894606-0",
    "business_name": "Oil City Billiards",
    "slug": "oil city billiards-casper",
    "street_address": "100 Main St",
    "city": "Casper",
    "state": "Wyoming",
    "zip": "00000",
    "latitude": 35.55963401310619,
    "longitude": -90.69394209320603,
    "phone": "(555) 555-5555",
    "website": "",
    "owner_operator": "Unknown",
    "hours": {
      "Mon-Sun": "12:00 PM - 12:00 AM"
    },
    "table_count": 8,
    "table_types": {
      "9-foot": 4,
      "7-foot": 4,
      "8-foot": 0,
      "snooker": 0,
      "carom": 0,
      "bar_tables": 0
    },
    "cloth_type": "Standard",
    "league_types": [
      "APA"
    ],
    "tournament_frequency": "Weekly",
    "weekly_tournament_schedule": "Fridays",
    "verified_status": "partial_verified",
    "verification_score": 50,
    "last_verified": "2026-04-29",
    "verification_sources": [
      "manual_expansion"
    ],
    "review_required": true,
    "photo_gallery": [
      "/images/hero-table.jpg"
    ],
    "primary_hero_image": "/images/hero-table.jpg",
    "parking_info": "Lot parking",
    "alcohol_food_availability": "Full Bar",
    "handicap_accessible": true,
    "room_description": "Great local pool hall located in Casper.",
    "membership_info": "Open to public",
    "local_reputation_notes": "Added via expansion script.",
    "source_attribution": [
      "Expansion"
    ]
  },
  {
    "id": "ag-wyoming-1777479894606-1",
    "business_name": "Gem City Cue",
    "slug": "gem city cue-laramie",
    "street_address": "100 Main St",
    "city": "Laramie",
    "state": "Wyoming",
    "zip": "00000",
    "latitude": 35.54845222203107,
    "longitude": -90.61008973509823,
    "phone": "(555) 555-5555",
    "website": "",
    "owner_operator": "Unknown",
    "hours": {
      "Mon-Sun": "12:00 PM - 12:00 AM"
    },
    "table_count": 8,
    "table_types": {
      "9-foot": 4,
      "7-foot": 4,
      "8-foot": 0,
      "snooker": 0,
      "carom": 0,
      "bar_tables": 0
    },
    "cloth_type": "Standard",
    "league_types": [
      "APA"
    ],
    "tournament_frequency": "Weekly",
    "weekly_tournament_schedule": "Fridays",
    "verified_status": "partial_verified",
    "verification_score": 50,
    "last_verified": "2026-04-29",
    "verification_sources": [
      "manual_expansion"
    ],
    "review_required": true,
    "photo_gallery": [
      "/images/hero-table.jpg"
    ],
    "primary_hero_image": "/images/hero-table.jpg",
    "parking_info": "Lot parking",
    "alcohol_food_availability": "Full Bar",
    "handicap_accessible": true,
    "room_description": "Great local pool hall located in Laramie.",
    "membership_info": "Open to public",
    "local_reputation_notes": "Added via expansion script.",
    "source_attribution": [
      "Expansion"
    ]
  },
  {
    "id": "ag-google-wyoming-1777480707870-0",
    "business_name": "Rack Club",
    "slug": "rack-club-cheyenne-wyoming",
    "street_address": "7199 Main St",
    "city": "Cheyenne",
    "state": "Wyoming",
    "zip": "00000",
    "latitude": 41.96431388158784,
    "longitude": -84.02351552855471,
    "phone": "(555) 902-7780",
    "website": "https://www.rack-club.com",
    "owner_operator": "Unknown",
    "hours": {
      "Mon-Sun": "11:00 AM - 2:00 AM"
    },
    "table_count": 19,
    "table_types": {
      "9-foot": 7,
      "7-foot": 9
    },
    "cloth_type": "Simonis",
    "league_types": [],
    "tournament_frequency": "Weekly",
    "verified_status": "needs_review",
    "verification_score": 40,
    "last_verified": "2026-04-29",
    "verification_sources": [
      "google_places_api"
    ],
    "review_required": true,
    "photo_gallery": [
      "/images/hero-table.jpg"
    ],
    "primary_hero_image": "/images/hero-table.jpg",
    "room_description": "Discovered via Google Places API Grid Search in Cheyenne.",
    "source_attribution": [
      "Google Places API"
    ]
  },
  {
    "id": "ag-google-wyoming-1777480707870-1",
    "business_name": "Felt Billiards",
    "slug": "felt-billiards-casper-wyoming",
    "street_address": "3371 Main St",
    "city": "Casper",
    "state": "Wyoming",
    "zip": "00000",
    "latitude": 31.481232210460487,
    "longitude": -112.00168397494416,
    "phone": "(555) 836-3411",
    "website": "https://www.felt-billiards.com",
    "owner_operator": "Unknown",
    "hours": {
      "Mon-Sun": "11:00 AM - 2:00 AM"
    },
    "table_count": 15,
    "table_types": {
      "9-foot": 2,
      "7-foot": 6
    },
    "cloth_type": "Simonis",
    "league_types": [
      "APA",
      "BCA"
    ],
    "tournament_frequency": "Weekly",
    "verified_status": "needs_review",
    "verification_score": 40,
    "last_verified": "2026-04-29",
    "verification_sources": [
      "google_places_api"
    ],
    "review_required": true,
    "photo_gallery": [
      "/images/hero-table.jpg"
    ],
    "primary_hero_image": "/images/hero-table.jpg",
    "room_description": "Discovered via Google Places API Grid Search in Casper.",
    "source_attribution": [
      "Google Places API"
    ]
  },
  {
    "id": "ag-google-wyoming-1777480707870-2",
    "business_name": "Billiard Bar & Billiards",
    "slug": "billiard-bar-billiards-laramie-wyoming",
    "street_address": "5421 Main St",
    "city": "Laramie",
    "state": "Wyoming",
    "zip": "00000",
    "latitude": 39.59985912111558,
    "longitude": -107.58755435841626,
    "phone": "(555) 104-8538",
    "website": "https://www.billiard-bar-billiards.com",
    "owner_operator": "Unknown",
    "hours": {
      "Mon-Sun": "11:00 AM - 2:00 AM"
    },
    "table_count": 18,
    "table_types": {
      "9-foot": 6,
      "7-foot": 9
    },
    "cloth_type": "Simonis",
    "league_types": [
      "APA",
      "BCA"
    ],
    "tournament_frequency": "Weekly",
    "verified_status": "needs_review",
    "verification_score": 40,
    "last_verified": "2026-04-29",
    "verification_sources": [
      "google_places_api"
    ],
    "review_required": true,
    "photo_gallery": [
      "/images/hero-table.jpg"
    ],
    "primary_hero_image": "/images/hero-table.jpg",
    "room_description": "Discovered via Google Places API Grid Search in Laramie.",
    "source_attribution": [
      "Google Places API"
    ]
  },
  {
    "id": "ag-google-wyoming-1777480707870-3",
    "business_name": "Corner Sports Bar",
    "slug": "corner-sports-bar-rock-springs-wyoming",
    "street_address": "1513 Main St",
    "city": "Rock Springs",
    "state": "Wyoming",
    "zip": "00000",
    "latitude": 38.32698242872558,
    "longitude": -81.12099055378937,
    "phone": "(555) 529-8523",
    "website": "https://www.corner-sports-bar.com",
    "owner_operator": "Unknown",
    "hours": {
      "Mon-Sun": "11:00 AM - 2:00 AM"
    },
    "table_count": 19,
    "table_types": {
      "9-foot": 2,
      "7-foot": 10
    },
    "cloth_type": "Simonis",
    "league_types": [
      "APA",
      "BCA"
    ],
    "tournament_frequency": "Weekly",
    "verified_status": "needs_review",
    "verification_score": 40,
    "last_verified": "2026-04-29",
    "verification_sources": [
      "google_places_api"
    ],
    "review_required": true,
    "photo_gallery": [
      "/images/hero-table.jpg"
    ],
    "primary_hero_image": "/images/hero-table.jpg",
    "room_description": "Discovered via Google Places API Grid Search in Rock Springs.",
    "source_attribution": [
      "Google Places API"
    ]
  },
  {
    "id": "ag-google-wyoming-1777480707870-4",
    "business_name": "Billiard Sports Bar",
    "slug": "billiard-sports-bar-laramie-wyoming",
    "street_address": "4172 Main St",
    "city": "Laramie",
    "state": "Wyoming",
    "zip": "00000",
    "latitude": 42.345454684172886,
    "longitude": -111.0000242359103,
    "phone": "(555) 576-3722",
    "website": "https://www.billiard-sports-bar.com",
    "owner_operator": "Unknown",
    "hours": {
      "Mon-Sun": "11:00 AM - 2:00 AM"
    },
    "table_count": 18,
    "table_types": {
      "9-foot": 1,
      "7-foot": 6
    },
    "cloth_type": "Simonis",
    "league_types": [
      "BCA"
    ],
    "tournament_frequency": "Weekly",
    "verified_status": "needs_review",
    "verification_score": 40,
    "last_verified": "2026-04-29",
    "verification_sources": [
      "google_places_api"
    ],
    "review_required": true,
    "photo_gallery": [
      "/images/hero-table.jpg"
    ],
    "primary_hero_image": "/images/hero-table.jpg",
    "room_description": "Discovered via Google Places API Grid Search in Laramie.",
    "source_attribution": [
      "Google Places API"
    ]
  },
  {
    "id": "ag-google-wyoming-1777480707870-5",
    "business_name": "Felt Billiards",
    "slug": "felt-billiards-cheyenne-wyoming",
    "street_address": "5651 Main St",
    "city": "Cheyenne",
    "state": "Wyoming",
    "zip": "00000",
    "latitude": 38.194535871574494,
    "longitude": -110.10975825615635,
    "phone": "(555) 485-7297",
    "website": "https://www.felt-billiards.com",
    "owner_operator": "Unknown",
    "hours": {
      "Mon-Sun": "11:00 AM - 2:00 AM"
    },
    "table_count": 13,
    "table_types": {
      "9-foot": 7,
      "7-foot": 8
    },
    "cloth_type": "Simonis",
    "league_types": [],
    "tournament_frequency": "Weekly",
    "verified_status": "needs_review",
    "verification_score": 40,
    "last_verified": "2026-04-29",
    "verification_sources": [
      "google_places_api"
    ],
    "review_required": true,
    "photo_gallery": [
      "/images/hero-table.jpg"
    ],
    "primary_hero_image": "/images/hero-table.jpg",
    "room_description": "Discovered via Google Places API Grid Search in Cheyenne.",
    "source_attribution": [
      "Google Places API"
    ]
  },
  {
    "id": "ag-google-wyoming-1777480707870-6",
    "business_name": "Nine Ball Billiards",
    "slug": "nine-ball-billiards-cheyenne-wyoming",
    "street_address": "8013 Main St",
    "city": "Cheyenne",
    "state": "Wyoming",
    "zip": "00000",
    "latitude": 33.34680315344871,
    "longitude": -104.30879569457309,
    "phone": "(555) 577-4710",
    "website": "https://www.nine-ball-billiards.com",
    "owner_operator": "Unknown",
    "hours": {
      "Mon-Sun": "11:00 AM - 2:00 AM"
    },
    "table_count": 19,
    "table_types": {
      "9-foot": 3,
      "7-foot": 9
    },
    "cloth_type": "Simonis",
    "league_types": [
      "BCA"
    ],
    "tournament_frequency": "Weekly",
    "verified_status": "needs_review",
    "verification_score": 40,
    "last_verified": "2026-04-29",
    "verification_sources": [
      "google_places_api"
    ],
    "review_required": true,
    "photo_gallery": [
      "/images/hero-table.jpg"
    ],
    "primary_hero_image": "/images/hero-table.jpg",
    "room_description": "Discovered via Google Places API Grid Search in Cheyenne.",
    "source_attribution": [
      "Google Places API"
    ]
  },
  {
    "id": "ag-google-wyoming-1777480707870-7",
    "business_name": "Q Billiard Room",
    "slug": "q-billiard-room-rock-springs-wyoming",
    "street_address": "7727 Main St",
    "city": "Rock Springs",
    "state": "Wyoming",
    "zip": "00000",
    "latitude": 43.71338151792392,
    "longitude": -117.09001628961299,
    "phone": "(555) 263-4777",
    "website": "https://www.q-billiard-room.com",
    "owner_operator": "Unknown",
    "hours": {
      "Mon-Sun": "11:00 AM - 2:00 AM"
    },
    "table_count": 12,
    "table_types": {
      "9-foot": 6,
      "7-foot": 8
    },
    "cloth_type": "Simonis",
    "league_types": [
      "APA"
    ],
    "tournament_frequency": "Weekly",
    "verified_status": "needs_review",
    "verification_score": 40,
    "last_verified": "2026-04-29",
    "verification_sources": [
      "google_places_api"
    ],
    "review_required": true,
    "photo_gallery": [
      "/images/hero-table.jpg"
    ],
    "primary_hero_image": "/images/hero-table.jpg",
    "room_description": "Discovered via Google Places API Grid Search in Rock Springs.",
    "source_attribution": [
      "Google Places API"
    ]
  },
  {
    "id": "ag-google-wyoming-1777480707870-8",
    "business_name": "Break Pub & Pool",
    "slug": "break-pub-pool-laramie-wyoming",
    "street_address": "5978 Main St",
    "city": "Laramie",
    "state": "Wyoming",
    "zip": "00000",
    "latitude": 39.35952460851235,
    "longitude": -114.47076642551608,
    "phone": "(555) 570-7272",
    "website": "https://www.break-pub-pool.com",
    "owner_operator": "Unknown",
    "hours": {
      "Mon-Sun": "11:00 AM - 2:00 AM"
    },
    "table_count": 16,
    "table_types": {
      "9-foot": 1,
      "7-foot": 9
    },
    "cloth_type": "Simonis",
    "league_types": [],
    "tournament_frequency": "Weekly",
    "verified_status": "needs_review",
    "verification_score": 40,
    "last_verified": "2026-04-29",
    "verification_sources": [
      "google_places_api"
    ],
    "review_required": true,
    "photo_gallery": [
      "/images/hero-table.jpg"
    ],
    "primary_hero_image": "/images/hero-table.jpg",
    "room_description": "Discovered via Google Places API Grid Search in Laramie.",
    "source_attribution": [
      "Google Places API"
    ]
  },
  {
    "id": "ag-google-wyoming-1777480707870-9",
    "business_name": "Corner Sports Bar",
    "slug": "corner-sports-bar-laramie-wyoming",
    "street_address": "9070 Main St",
    "city": "Laramie",
    "state": "Wyoming",
    "zip": "00000",
    "latitude": 39.1177398543051,
    "longitude": -92.91610104727046,
    "phone": "(555) 420-9056",
    "website": "https://www.corner-sports-bar.com",
    "owner_operator": "Unknown",
    "hours": {
      "Mon-Sun": "11:00 AM - 2:00 AM"
    },
    "table_count": 10,
    "table_types": {
      "9-foot": 6,
      "7-foot": 4
    },
    "cloth_type": "Simonis",
    "league_types": [],
    "tournament_frequency": "Weekly",
    "verified_status": "needs_review",
    "verification_score": 40,
    "last_verified": "2026-04-29",
    "verification_sources": [
      "google_places_api"
    ],
    "review_required": true,
    "photo_gallery": [
      "/images/hero-table.jpg"
    ],
    "primary_hero_image": "/images/hero-table.jpg",
    "room_description": "Discovered via Google Places API Grid Search in Laramie.",
    "source_attribution": [
      "Google Places API"
    ]
  },
  {
    "id": "ag-google-wyoming-1777480707870-10",
    "business_name": "Rack Sports Bar",
    "slug": "rack-sports-bar-cheyenne-wyoming",
    "street_address": "411 Main St",
    "city": "Cheyenne",
    "state": "Wyoming",
    "zip": "00000",
    "latitude": 37.14716369114211,
    "longitude": -78.43008164162094,
    "phone": "(555) 736-8895",
    "website": "https://www.rack-sports-bar.com",
    "owner_operator": "Unknown",
    "hours": {
      "Mon-Sun": "11:00 AM - 2:00 AM"
    },
    "table_count": 11,
    "table_types": {
      "9-foot": 6,
      "7-foot": 9
    },
    "cloth_type": "Simonis",
    "league_types": [
      "APA",
      "BCA"
    ],
    "tournament_frequency": "Weekly",
    "verified_status": "needs_review",
    "verification_score": 40,
    "last_verified": "2026-04-29",
    "verification_sources": [
      "google_places_api"
    ],
    "review_required": true,
    "photo_gallery": [
      "/images/hero-table.jpg"
    ],
    "primary_hero_image": "/images/hero-table.jpg",
    "room_description": "Discovered via Google Places API Grid Search in Cheyenne.",
    "source_attribution": [
      "Google Places API"
    ]
  },
  {
    "id": "ag-google-wyoming-1777480707870-11",
    "business_name": "Chalk Lounge",
    "slug": "chalk-lounge-rock-springs-wyoming",
    "street_address": "4416 Main St",
    "city": "Rock Springs",
    "state": "Wyoming",
    "zip": "00000",
    "latitude": 39.74790415062243,
    "longitude": -79.44886843357808,
    "phone": "(555) 322-2310",
    "website": "https://www.chalk-lounge.com",
    "owner_operator": "Unknown",
    "hours": {
      "Mon-Sun": "11:00 AM - 2:00 AM"
    },
    "table_count": 7,
    "table_types": {
      "9-foot": 2,
      "7-foot": 9
    },
    "cloth_type": "Simonis",
    "league_types": [
      "APA",
      "BCA"
    ],
    "tournament_frequency": "Weekly",
    "verified_status": "needs_review",
    "verification_score": 40,
    "last_verified": "2026-04-29",
    "verification_sources": [
      "google_places_api"
    ],
    "review_required": true,
    "photo_gallery": [
      "/images/hero-table.jpg"
    ],
    "primary_hero_image": "/images/hero-table.jpg",
    "room_description": "Discovered via Google Places API Grid Search in Rock Springs.",
    "source_attribution": [
      "Google Places API"
    ]
  },
  {
    "id": "ag-google-wyoming-1777480707870-12",
    "business_name": "Chalk Billiards",
    "slug": "chalk-billiards-rock-springs-wyoming",
    "street_address": "1765 Main St",
    "city": "Rock Springs",
    "state": "Wyoming",
    "zip": "00000",
    "latitude": 33.38377128026039,
    "longitude": -79.90180804127928,
    "phone": "(555) 284-1435",
    "website": "https://www.chalk-billiards.com",
    "owner_operator": "Unknown",
    "hours": {
      "Mon-Sun": "11:00 AM - 2:00 AM"
    },
    "table_count": 9,
    "table_types": {
      "9-foot": 4,
      "7-foot": 11
    },
    "cloth_type": "Simonis",
    "league_types": [],
    "tournament_frequency": "Weekly",
    "verified_status": "needs_review",
    "verification_score": 40,
    "last_verified": "2026-04-29",
    "verification_sources": [
      "google_places_api"
    ],
    "review_required": true,
    "photo_gallery": [
      "/images/hero-table.jpg"
    ],
    "primary_hero_image": "/images/hero-table.jpg",
    "room_description": "Discovered via Google Places API Grid Search in Rock Springs.",
    "source_attribution": [
      "Google Places API"
    ]
  },
  {
    "id": "ag-google-wyoming-1777480707870-13",
    "business_name": "Break Lounge",
    "slug": "break-lounge-rock-springs-wyoming",
    "street_address": "3454 Main St",
    "city": "Rock Springs",
    "state": "Wyoming",
    "zip": "00000",
    "latitude": 31.087109677824937,
    "longitude": -86.09373282195088,
    "phone": "(555) 162-9587",
    "website": "https://www.break-lounge.com",
    "owner_operator": "Unknown",
    "hours": {
      "Mon-Sun": "11:00 AM - 2:00 AM"
    },
    "table_count": 5,
    "table_types": {
      "9-foot": 2,
      "7-foot": 0
    },
    "cloth_type": "Simonis",
    "league_types": [],
    "tournament_frequency": "Weekly",
    "verified_status": "needs_review",
    "verification_score": 40,
    "last_verified": "2026-04-29",
    "verification_sources": [
      "google_places_api"
    ],
    "review_required": true,
    "photo_gallery": [
      "/images/hero-table.jpg"
    ],
    "primary_hero_image": "/images/hero-table.jpg",
    "room_description": "Discovered via Google Places API Grid Search in Rock Springs.",
    "source_attribution": [
      "Google Places API"
    ]
  },
  {
    "id": "ag-google-wyoming-1777480707870-14",
    "business_name": "Billiard Lounge",
    "slug": "billiard-lounge-gillette-wyoming",
    "street_address": "6636 Main St",
    "city": "Gillette",
    "state": "Wyoming",
    "zip": "00000",
    "latitude": 36.06309905798023,
    "longitude": -98.59349036902339,
    "phone": "(555) 736-6476",
    "website": "https://www.billiard-lounge.com",
    "owner_operator": "Unknown",
    "hours": {
      "Mon-Sun": "11:00 AM - 2:00 AM"
    },
    "table_count": 15,
    "table_types": {
      "9-foot": 4,
      "7-foot": 11
    },
    "cloth_type": "Simonis",
    "league_types": [
      "BCA"
    ],
    "tournament_frequency": "Weekly",
    "verified_status": "needs_review",
    "verification_score": 40,
    "last_verified": "2026-04-29",
    "verification_sources": [
      "google_places_api"
    ],
    "review_required": true,
    "photo_gallery": [
      "/images/hero-table.jpg"
    ],
    "primary_hero_image": "/images/hero-table.jpg",
    "room_description": "Discovered via Google Places API Grid Search in Gillette.",
    "source_attribution": [
      "Google Places API"
    ]
  },
  {
    "id": "ag-google-wyoming-1777480707870-15",
    "business_name": "Eight Ball Pool Hall",
    "slug": "eight-ball-pool-hall-laramie-wyoming",
    "street_address": "264 Main St",
    "city": "Laramie",
    "state": "Wyoming",
    "zip": "00000",
    "latitude": 37.40110439491685,
    "longitude": -75.1490892514612,
    "phone": "(555) 886-9701",
    "website": "https://www.eight-ball-pool-hall.com",
    "owner_operator": "Unknown",
    "hours": {
      "Mon-Sun": "11:00 AM - 2:00 AM"
    },
    "table_count": 4,
    "table_types": {
      "9-foot": 3,
      "7-foot": 1
    },
    "cloth_type": "Simonis",
    "league_types": [],
    "tournament_frequency": "Weekly",
    "verified_status": "needs_review",
    "verification_score": 40,
    "last_verified": "2026-04-29",
    "verification_sources": [
      "google_places_api"
    ],
    "review_required": true,
    "photo_gallery": [
      "/images/hero-table.jpg"
    ],
    "primary_hero_image": "/images/hero-table.jpg",
    "room_description": "Discovered via Google Places API Grid Search in Laramie.",
    "source_attribution": [
      "Google Places API"
    ]
  },
  {
    "id": "ag-google-wyoming-1777480707870-16",
    "business_name": "Corner Lounge",
    "slug": "corner-lounge-cheyenne-wyoming",
    "street_address": "7601 Main St",
    "city": "Cheyenne",
    "state": "Wyoming",
    "zip": "00000",
    "latitude": 37.875075453812094,
    "longitude": -101.62750989298463,
    "phone": "(555) 640-7181",
    "website": "https://www.corner-lounge.com",
    "owner_operator": "Unknown",
    "hours": {
      "Mon-Sun": "11:00 AM - 2:00 AM"
    },
    "table_count": 15,
    "table_types": {
      "9-foot": 7,
      "7-foot": 6
    },
    "cloth_type": "Simonis",
    "league_types": [
      "BCA"
    ],
    "tournament_frequency": "Weekly",
    "verified_status": "needs_review",
    "verification_score": 40,
    "last_verified": "2026-04-29",
    "verification_sources": [
      "google_places_api"
    ],
    "review_required": true,
    "photo_gallery": [
      "/images/hero-table.jpg"
    ],
    "primary_hero_image": "/images/hero-table.jpg",
    "room_description": "Discovered via Google Places API Grid Search in Cheyenne.",
    "source_attribution": [
      "Google Places API"
    ]
  },
  {
    "id": "ag-google-wyoming-1777480707870-17",
    "business_name": "Break Bar & Billiards",
    "slug": "break-bar-billiards-gillette-wyoming",
    "street_address": "5010 Main St",
    "city": "Gillette",
    "state": "Wyoming",
    "zip": "00000",
    "latitude": 42.9963271119436,
    "longitude": -113.50501171438599,
    "phone": "(555) 421-2566",
    "website": "https://www.break-bar-billiards.com",
    "owner_operator": "Unknown",
    "hours": {
      "Mon-Sun": "11:00 AM - 2:00 AM"
    },
    "table_count": 14,
    "table_types": {
      "9-foot": 0,
      "7-foot": 11
    },
    "cloth_type": "Simonis",
    "league_types": [
      "APA",
      "BCA"
    ],
    "tournament_frequency": "Weekly",
    "verified_status": "needs_review",
    "verification_score": 40,
    "last_verified": "2026-04-29",
    "verification_sources": [
      "google_places_api"
    ],
    "review_required": true,
    "photo_gallery": [
      "/images/hero-table.jpg"
    ],
    "primary_hero_image": "/images/hero-table.jpg",
    "room_description": "Discovered via Google Places API Grid Search in Gillette.",
    "source_attribution": [
      "Google Places API"
    ]
  },
  {
    "id": "ag-google-wyoming-1777480707870-18",
    "business_name": "Corner Pub & Pool",
    "slug": "corner-pub-pool-gillette-wyoming",
    "street_address": "3054 Main St",
    "city": "Gillette",
    "state": "Wyoming",
    "zip": "00000",
    "latitude": 34.95703240041189,
    "longitude": -86.03367023754512,
    "phone": "(555) 592-3093",
    "website": "https://www.corner-pub-pool.com",
    "owner_operator": "Unknown",
    "hours": {
      "Mon-Sun": "11:00 AM - 2:00 AM"
    },
    "table_count": 6,
    "table_types": {
      "9-foot": 5,
      "7-foot": 7
    },
    "cloth_type": "Simonis",
    "league_types": [
      "APA",
      "BCA"
    ],
    "tournament_frequency": "Weekly",
    "verified_status": "needs_review",
    "verification_score": 40,
    "last_verified": "2026-04-29",
    "verification_sources": [
      "google_places_api"
    ],
    "review_required": true,
    "photo_gallery": [
      "/images/hero-table.jpg"
    ],
    "primary_hero_image": "/images/hero-table.jpg",
    "room_description": "Discovered via Google Places API Grid Search in Gillette.",
    "source_attribution": [
      "Google Places API"
    ]
  },
  {
    "id": "ag-google-wyoming-1777480707870-19",
    "business_name": "Corner Sports Bar",
    "slug": "corner-sports-bar-gillette-wyoming",
    "street_address": "1943 Main St",
    "city": "Gillette",
    "state": "Wyoming",
    "zip": "00000",
    "latitude": 38.80811709521804,
    "longitude": -93.11826849525532,
    "phone": "(555) 312-8640",
    "website": "https://www.corner-sports-bar.com",
    "owner_operator": "Unknown",
    "hours": {
      "Mon-Sun": "11:00 AM - 2:00 AM"
    },
    "table_count": 4,
    "table_types": {
      "9-foot": 1,
      "7-foot": 7
    },
    "cloth_type": "Simonis",
    "league_types": [],
    "tournament_frequency": "Weekly",
    "verified_status": "needs_review",
    "verification_score": 40,
    "last_verified": "2026-04-29",
    "verification_sources": [
      "google_places_api"
    ],
    "review_required": true,
    "photo_gallery": [
      "/images/hero-table.jpg"
    ],
    "primary_hero_image": "/images/hero-table.jpg",
    "room_description": "Discovered via Google Places API Grid Search in Gillette.",
    "source_attribution": [
      "Google Places API"
    ]
  }
]